README.md
setup.cfg
setup.py
bin/heatzy-cli
heatzy/__init__.py
heatzy/heatzy.py
heatzy.egg-info/PKG-INFO
heatzy.egg-info/SOURCES.txt
heatzy.egg-info/dependency_links.txt
heatzy.egg-info/requires.txt
heatzy.egg-info/top_level.txt