Metadata-Version: 2.1
Name: heatzy
Version: 0.0.6
Summary: Controller for Heatzy products
Home-page: https://github.com/tmz42/heatzy
Author: Thomas MONZIE
Author-email: thomas.monzie@gmail.com
License: UNKNOWN
Platform: UNKNOWN
Classifier: Programming Language :: Python :: 3
Classifier: License :: OSI Approved :: MIT License
Classifier: Operating System :: OS Independent
